fntpl/main.py
fntpl/template_functions.py
fntpl-0.1.0.dist-info/METADATA
fntpl-0.1.0.dist-info/WHEEL
fntpl-0.1.0.dist-info/entry_points.txt
fntpl-0.1.0.dist-info/top_level.txt
fntpl-0.1.0.dist-info/RECORD
