Metadata-Version: 2.4
Name: fntpl
Version: 0.1.0
Summary: The template engine for naming new files.
Author: 4evsec
Project-URL: Repository, https://github.com/4evsec/fntpl
Project-URL: Issues, https://github.com/4evsec/fntpl/issues
Requires-Python: >=3.14
Requires-Dist: jinja2>=3.1.6
